recipe_clipper/__init__.py
recipe_clipper/cli.py
recipe_clipper/clipper.py
recipe_clipper/exceptions.py
recipe_clipper/formatters.py
recipe_clipper/http.py
recipe_clipper/models.py
recipe_clipper/parsers/__init__.py
recipe_clipper/parsers/llm_parser.py
recipe_clipper/parsers/recipe_scrapers_parser.py
recipe_clipper-0.1.0a0.dist-info/METADATA
recipe_clipper-0.1.0a0.dist-info/WHEEL
recipe_clipper-0.1.0a0.dist-info/entry_points.txt
recipe_clipper-0.1.0a0.dist-info/licenses/LICENSE
recipe_clipper-0.1.0a0.dist-info/RECORD
