Metadata-Version: 2.4
Name: recipe-clipper
Version: 0.1.0a0
Summary: Extract recipes from websites, images, and documents.
Project-URL: Homepage, https://github.com/zduey/recipe-clipper
Project-URL: Repository, https://github.com/zduey/recipe-clipper
Project-URL: Issues, https://github.com/zduey/recipe-clipper/issues
Author: Recipe Clipper Contributors
License: MIT
License-File: LICENSE
Keywords: cooking,food,llm,ocr,parser,pdf,recipe,scraping,vision
Classifier: Development Status :: 3 - Alpha
Classifier: Intended Audience :: Developers
Classifier: Intended Audience :: End Users/Desktop
Classifier: License :: OSI Approved :: MIT License
Classifier: Programming Language :: Python :: 3
Classifier: Programming Language :: Python :: 3.9
Classifier: Programming Language :: Python :: 3.10
Classifier: Programming Language :: Python :: 3.11
Classifier: Programming Language :: Python :: 3.12
Classifier: Programming Language :: Python :: 3.13
Classifier: Programming Language :: Python :: 3.14
Classifier: Topic :: Software Development :: Libraries :: Python Modules
Classifier: Topic :: Text Processing :: Markup :: HTML
Classifier: Topic :: Utilities
Requires-Python: >=3.9
Requires-Dist: httpx>=0.27.0
Requires-Dist: pydantic>=2.0.0
Requires-Dist: python-dotenv>=1.0.0
Requires-Dist: recipe-scrapers>=15.0.0
Requires-Dist: rich>=13.0.0
Requires-Dist: typer>=0.12.0
Provides-Extra: dev
Requires-Dist: pytest-asyncio>=0.23.0; extra == 'dev'
Requires-Dist: pytest-cov>=4.1.0; extra == 'dev'
Requires-Dist: pytest>=8.0.0; extra == 'dev'
Requires-Dist: respx>=0.21.0; extra == 'dev'
Provides-Extra: llm
Requires-Dist: anthropic>=0.40.0; extra == 'llm'
Requires-Dist: cohere>=5.0.0; extra == 'llm'
Requires-Dist: google-generativeai>=0.3.0; extra == 'llm'
Requires-Dist: openai>=1.0.0; extra == 'llm'
Provides-Extra: llm-anthropic
Requires-Dist: anthropic>=0.40.0; extra == 'llm-anthropic'
Provides-Extra: llm-cohere
Requires-Dist: cohere>=5.0.0; extra == 'llm-cohere'
Provides-Extra: llm-google
Requires-Dist: google-generativeai>=0.3.0; extra == 'llm-google'
Provides-Extra: llm-openai
Requires-Dist: openai>=1.0.0; extra == 'llm-openai'
